{
  "crawledAt": "2026-04-11T01:11:13.296589",
  "count": 60,
  "articles": [
    {
      "title": "베인캐피탈, '최윤범 백기사' 엑시트…메리츠금융이 바통 터치[주간사모펀드]",
      "summary": "JKL파트너스, 롯데손보 주관사 교체로 매각 재시동 스틱·한투 컨소, SK 에너지 인프라 품어 영풍·MBK파트너스 연합과 최윤범 고려아..",
      "url": "https://finance.naver.com/news/news_read.naver?article_id=0000490443&office_id=629&mode=mainnews&type=&date=2026-04-11&page=1",
      "date": "",
      "source": ""
    },
    {
      "title": "[주식 매매 상위 종목 및 환율] 2026년 4월 10일자",
      "summary": "",
      "url": "https://finance.naver.com/news/news_read.naver?article_id=0003970193&office_id=023&mode=LSS2D&type=0&section_id=101&section_id2=258&section_id3=&date=20260411&page=1",
      "date": "",
      "source": ""
    },
    {
      "title": "\"자산관리 서비스 강화\"…신한투자증권, '프리미어 특화 세미나' 개최",
      "summary": "",
      "url": "https://finance.naver.com/news/news_read.naver?article_id=0003079426&office_id=119&mode=LSS2D&type=0&section_id=101&section_id2=258&section_id3=&date=20260411&page=1",
      "date": "",
      "source": ""
    },
    {
      "title": "[주간사모펀드] 베인캐피탈, '최윤범 백기사' 엑시트…메리츠금융이 바통 터치",
      "summary": "",
      "url": "https://finance.naver.com/news/news_read.naver?article_id=0000490443&office_id=629&mode=LSS2D&type=0&section_id=101&section_id2=258&section_id3=&date=20260411&page=1",
      "date": "",
      "source": ""
    },
    {
      "title": "美 3월 CPI 예상치 하회에도 불확실성↑…인플레 재점화 우려 '고개'",
      "summary": "",
      "url": "https://finance.naver.com/news/news_read.naver?article_id=0000490436&office_id=629&mode=LSS2D&type=0&section_id=101&section_id2=258&section_id3=&date=20260411&page=1",
      "date": "",
      "source": ""
    },
    {
      "title": "[올댓차이나] 中, 창업판 개혁 가속…마켓메이커 도입·지수선물 추진",
      "summary": "",
      "url": "https://finance.naver.com/news/news_read.naver?article_id=0013881286&office_id=003&mode=LSS2D&type=0&section_id=101&section_id2=258&section_id3=&date=20260411&page=1",
      "date": "",
      "source": ""
    },
    {
      "title": "[속보] 美 3월 CPI 전년比 3.3% 상승…시장 예상치 하회",
      "summary": "",
      "url": "https://finance.naver.com/news/news_read.naver?article_id=0000490426&office_id=629&mode=LSS2D&type=0&section_id=101&section_id2=258&section_id3=&date=20260411&page=1",
      "date": "",
      "source": ""
    },
    {
      "title": "종전 협상 결과가 정할 코스피 방향성…시장 주목",
      "summary": "",
      "url": "https://finance.naver.com/news/news_read.naver?article_id=0000853785&office_id=422&mode=LSS2D&type=0&section_id=101&section_id2=258&section_id3=&date=20260411&page=1",
      "date": "",
      "source": ""
    },
    {
      "title": "국내에서 가장 비싼 주식인데...“410만 원 간다” 목표가 또 올랐다",
      "summary": "",
      "url": "https://finance.naver.com/news/news_read.naver?article_id=0004609513&office_id=011&mode=LSS2D&type=0&section_id=101&section_id2=258&section_id3=&date=20260411&page=1",
      "date": "",
      "source": ""
    },
    {
      "title": "한국GM, 수조 원대 첫 중간 배당한다…국내 철수설 불식 나서",
      "summary": "",
      "url": "https://finance.naver.com/news/news_read.naver?article_id=0003711483&office_id=020&mode=LSS2D&type=0&section_id=101&section_id2=258&section_id3=&date=20260411&page=1",
      "date": "",
      "source": ""
    },
    {
      "title": "지정학적 긴장 완화에 7만달러 돌파, 비트코인 상승의 진짜 이유[엠블록레터]",
      "summary": "",
      "url": "https://finance.naver.com/news/news_read.naver?article_id=0005664347&office_id=009&mode=LSS2D&type=0&section_id=101&section_id2=258&section_id3=&date=20260411&page=1",
      "date": "",
      "source": ""
    },
    {
      "title": "민주노총 \"피지컬 AI 걱정\"…이 대통령 \"너무 공포 가질 필요 없어\"",
      "summary": "",
      "url": "https://finance.naver.com/news/news_read.naver?article_id=0001944120&office_id=057&mode=LSS2D&type=0&section_id=101&section_id2=258&section_id3=&date=20260411&page=1",
      "date": "",
      "source": ""
    },
    {
      "title": "중동 사태에 자재 비상 '공사 지연'…\"사전점검 늦춰져\" 혼란",
      "summary": "",
      "url": "https://finance.naver.com/news/news_read.naver?article_id=0001944117&office_id=057&mode=LSS2D&type=0&section_id=101&section_id2=258&section_id3=&date=20260411&page=1",
      "date": "",
      "source": ""
    },
    {
      "title": "3차 최고가 동결에도 기름값 또 올라…\"올해 말까지 고유가\"",
      "summary": "",
      "url": "https://finance.naver.com/news/news_read.naver?article_id=0001944115&office_id=057&mode=LSS2D&type=0&section_id=101&section_id2=258&section_id3=&date=20260411&page=1",
      "date": "",
      "source": ""
    },
    {
      "title": "잠수함 화재 고립자 구조 진전 없어…HD현대중 \"사망\"",
      "summary": "",
      "url": "https://finance.naver.com/news/news_read.naver?article_id=0016015082&office_id=001&mode=LSS2D&type=0&section_id=101&section_id2=258&section_id3=&date=20260411&page=1",
      "date": "",
      "source": ""
    },
    {
      "title": "[올댓차이나] 대만 증시, 중동협상 기대에 나흘째 상승 최고치 경신…1.6%↑",
      "summary": "",
      "url": "https://finance.naver.com/news/news_read.naver?article_id=0013881122&office_id=003&mode=LSS2D&type=0&section_id=101&section_id2=258&section_id3=&date=20260411&page=1",
      "date": "",
      "source": ""
    },
    {
      "title": "'통항 준비' HMM 선박 1척 두바이로 이동…이란 \"한국 특사 환영\"",
      "summary": "",
      "url": "https://finance.naver.com/news/news_read.naver?article_id=0001944098&office_id=057&mode=LSS2D&type=0&section_id=101&section_id2=258&section_id3=&date=20260411&page=1",
      "date": "",
      "source": ""
    },
    {
      "title": "3개월새 ‘2배’ 껑충...“삼성‘전자’인 줄 알았는데 다시 보니 아니다?”",
      "summary": "",
      "url": "https://finance.naver.com/news/news_read.naver?article_id=0004609500&office_id=011&mode=LSS2D&type=0&section_id=101&section_id2=258&section_id3=&date=20260411&page=1",
      "date": "",
      "source": ""
    },
    {
      "title": "“하루에 6%씩 오르니까”…휴전 안도랠리에 코스피 추종 ETF 뭉칫돈",
      "summary": "",
      "url": "https://finance.naver.com/news/news_read.naver?article_id=0005664330&office_id=009&mode=LSS2D&type=0&section_id=101&section_id2=258&section_id3=&date=20260411&page=1",
      "date": "",
      "source": ""
    },
    {
      "title": "[올댓차이나] 홍콩 증시, 중동 선행 불안 완화에 반등 마감…H주 0.5%↑",
      "summary": "",
      "url": "https://finance.naver.com/news/news_read.naver?article_id=0013881078&office_id=003&mode=LSS2D&type=0&section_id=101&section_id2=258&section_id3=&date=20260411&page=1",
      "date": "",
      "source": ""
    },
    {
      "title": "기준금리, 7회 연속 동결… 중동사태 불확실성에 ‘관망 모드’",
      "summary": "",
      "url": "https://finance.naver.com/news/news_read.naver?article_id=0001842547&office_id=005&mode=LSS2D&type=0&section_id=101&section_id2=259&section_id3=&date=20260411&page=1",
      "date": "",
      "source": ""
    },
    {
      "title": "전쟁 추경 26.2조 국회 통과…대중교통 환급·나프타 수급 증액",
      "summary": "",
      "url": "https://finance.naver.com/news/news_read.naver?article_id=0008883322&office_id=421&mode=LSS2D&type=0&section_id=101&section_id2=259&section_id3=&date=20260411&page=1",
      "date": "",
      "source": ""
    },
    {
      "title": "HSBC·스탠다드차타드, 첫 홍콩달러 스테이블코인 발행사로 낙점",
      "summary": "",
      "url": "https://finance.naver.com/news/news_read.naver?article_id=0006254923&office_id=018&mode=LSS2D&type=0&section_id=101&section_id2=259&section_id3=&date=20260411&page=1",
      "date": "",
      "source": ""
    },
    {
      "title": "한국GM 11년 만에 주주환원 재개…창사 첫 중간배당 추진",
      "summary": "",
      "url": "https://finance.naver.com/news/news_read.naver?article_id=0000173550&office_id=656&mode=LSS2D&type=0&section_id=101&section_id2=259&section_id3=&date=20260411&page=1",
      "date": "",
      "source": ""
    },
    {
      "title": "국민연금 적립금 1540조원 돌파…수익금이 보험료 앞질러",
      "summary": "",
      "url": "https://finance.naver.com/news/news_read.naver?article_id=0002783885&office_id=021&mode=LSS2D&type=0&section_id=101&section_id2=259&section_id3=&date=20260411&page=1",
      "date": "",
      "source": ""
    },
    {
      "title": "환율 못 잡고 떠나는 이창용 \"트럼프가 도와주지 않는다\"",
      "summary": "",
      "url": "https://finance.naver.com/news/news_read.naver?article_id=0000173545&office_id=656&mode=LSS2D&type=0&section_id=101&section_id2=259&section_id3=&date=20260411&page=1",
      "date": "",
      "source": ""
    },
    {
      "title": "'큰 손' 변심했나…코스닥서 2300억 던진 배경은",
      "summary": "",
      "url": "https://finance.naver.com/news/news_read.naver?article_id=0001248635&office_id=215&mode=LSS2D&type=0&section_id=101&section_id2=259&section_id3=&date=20260411&page=1",
      "date": "",
      "source": ""
    },
    {
      "title": "2차 공공기관 이전 선거 쟁점화···대구시 'IBK' 유치 총력",
      "summary": "",
      "url": "https://finance.naver.com/news/news_read.naver?article_id=0000050286&office_id=657&mode=LSS2D&type=0&section_id=101&section_id2=259&section_id3=&date=20260411&page=1",
      "date": "",
      "source": ""
    },
    {
      "title": "스테이블코인 논쟁 격화…“금융과 충돌” Vs “전통 금융 대안”",
      "summary": "",
      "url": "https://finance.naver.com/news/news_read.naver?article_id=0006254876&office_id=018&mode=LSS2D&type=0&section_id=101&section_id2=259&section_id3=&date=20260411&page=1",
      "date": "",
      "source": ""
    },
    {
      "title": "일본, 가상자산 ‘금융상품’ 첫 규정…증권 수준 규제 도입(종합)",
      "summary": "",
      "url": "https://finance.naver.com/news/news_read.naver?article_id=0006254874&office_id=018&mode=LSS2D&type=0&section_id=101&section_id2=259&section_id3=&date=20260411&page=1",
      "date": "",
      "source": ""
    },
    {
      "title": "[마켓인]IVS 앞두고 쏟아진 日 VC 조언…“크지만 느린 시장”",
      "summary": "",
      "url": "https://finance.naver.com/news/news_read.naver?article_id=0006254866&office_id=018&mode=LSS2D&type=0&section_id=101&section_id2=259&section_id3=&date=20260411&page=1",
      "date": "",
      "source": ""
    },
    {
      "title": "일본, 가상자산 ‘금융상품’ 첫 규정…공시 의무화·부정행위 처벌강화",
      "summary": "",
      "url": "https://finance.naver.com/news/news_read.naver?article_id=0006254865&office_id=018&mode=LSS2D&type=0&section_id=101&section_id2=259&section_id3=&date=20260411&page=1",
      "date": "",
      "source": ""
    },
    {
      "title": "'미토스' 공개 직후…美재무, 월가 CEO들 불러 '긴급 회의'",
      "summary": "",
      "url": "https://finance.naver.com/news/news_read.naver?article_id=0001248626&office_id=215&mode=LSS2D&type=0&section_id=101&section_id2=259&section_id3=&date=20260411&page=1",
      "date": "",
      "source": ""
    },
    {
      "title": "영업정지 앞둔 롯데카드, 자산 부실 위험도",
      "summary": "",
      "url": "https://finance.naver.com/news/news_read.naver?article_id=0004609494&office_id=011&mode=LSS2D&type=0&section_id=101&section_id2=259&section_id3=&date=20260411&page=1",
      "date": "",
      "source": ""
    },
    {
      "title": "[마켓인]차 안 팔리니 나홀로 ‘돈 가뭄’…폭스바겐파이낸셜, 수중에 단돈 ‘46억’",
      "summary": "",
      "url": "https://finance.naver.com/news/news_read.naver?article_id=0006254856&office_id=018&mode=LSS2D&type=0&section_id=101&section_id2=259&section_id3=&date=20260411&page=1",
      "date": "",
      "source": ""
    },
    {
      "title": "'K-점도표' 도입부터 '입시개혁'까지…이창용 4년, 한은의 틀을 깼다",
      "summary": "",
      "url": "https://finance.naver.com/news/news_read.naver?article_id=0008883137&office_id=421&mode=LSS2D&type=0&section_id=101&section_id2=259&section_id3=&date=20260411&page=1",
      "date": "",
      "source": ""
    },
    {
      "title": "금융위, 국민참여형펀드 판매 목표액 20% 서민 우성 배정 검토",
      "summary": "",
      "url": "https://finance.naver.com/news/news_read.naver?article_id=0006254853&office_id=018&mode=LSS2D&type=0&section_id=101&section_id2=259&section_id3=&date=20260411&page=1",
      "date": "",
      "source": ""
    },
    {
      "title": "연금 계좌 효율 높이는 美 채권혼합형 ETF…올해 1000억 유입 [ETF 줌인]",
      "summary": "",
      "url": "https://finance.naver.com/news/news_read.naver?article_id=0004609481&office_id=011&mode=LSS2D&type=0&section_id=101&section_id2=259&section_id3=&date=20260411&page=1",
      "date": "",
      "source": ""
    },
    {
      "title": "국민참여형 국민성장펀드, 서민에 20% 이상 우선배정 검토",
      "summary": "",
      "url": "https://finance.naver.com/news/news_read.naver?article_id=0002627982&office_id=016&mode=LSS2D&type=0&section_id=101&section_id2=259&section_id3=&date=20260411&page=1",
      "date": "",
      "source": ""
    },
    {
      "title": "금융위원장, 암참 회장과 글로벌 금융허브 도약 논의",
      "summary": "",
      "url": "https://finance.naver.com/news/news_read.naver?article_id=0002627981&office_id=016&mode=LSS2D&type=0&section_id=101&section_id2=259&section_id3=&date=20260411&page=1",
      "date": "",
      "source": ""
    },
    {
      "title": "美 비축유 방출, 英 유류세 인하, 佛 보조금 지급… 가격 통제 드물어",
      "summary": "",
      "url": "https://finance.naver.com/news/news_read.naver?article_id=0003970218&office_id=023&mode=LSS2D&type=0&section_id=101&section_id2=261&section_id3=&date=20260411&page=1",
      "date": "",
      "source": ""
    },
    {
      "title": "검찰, ‘10조원대 전분·당류 담합’ 대상 대표 구속영장 재청구",
      "summary": "",
      "url": "https://finance.naver.com/news/news_read.naver?article_id=0002783898&office_id=021&mode=LSS2D&type=0&section_id=101&section_id2=261&section_id3=&date=20260411&page=1",
      "date": "",
      "source": ""
    },
    {
      "title": "종량제 봉투 계속 만들고 있어요",
      "summary": "",
      "url": "https://finance.naver.com/news/news_read.naver?article_id=0003970194&office_id=023&mode=LSS2D&type=0&section_id=101&section_id2=261&section_id3=&date=20260411&page=1",
      "date": "",
      "source": ""
    },
    {
      "title": "4년 연속 흑자 한국GM, 최대 4조원 중간배당",
      "summary": "",
      "url": "https://finance.naver.com/news/news_read.naver?article_id=0003970192&office_id=023&mode=LSS2D&type=0&section_id=101&section_id2=261&section_id3=&date=20260411&page=1",
      "date": "",
      "source": ""
    },
    {
      "title": "나프타 단가 상승분 50% 지원…산업부, 1조980억원 추경 확정",
      "summary": "",
      "url": "https://finance.naver.com/news/news_read.naver?article_id=0000853833&office_id=422&mode=LSS2D&type=0&section_id=101&section_id2=261&section_id3=&date=20260411&page=1",
      "date": "",
      "source": ""
    },
    {
      "title": "[사설] 비업무용 부동산 규제 강화, 기업 투자 위축은 없기를",
      "summary": "",
      "url": "https://finance.naver.com/news/news_read.naver?article_id=0004609533&office_id=011&mode=LSS2D&type=0&section_id=101&section_id2=261&section_id3=&date=20260411&page=1",
      "date": "",
      "source": ""
    },
    {
      "title": "산업부, 추경 1조980억 확정…나프타 수급지원에 6744억",
      "summary": "",
      "url": "https://finance.naver.com/news/news_read.naver?article_id=0008883354&office_id=421&mode=LSS2D&type=0&section_id=101&section_id2=261&section_id3=&date=20260411&page=1",
      "date": "",
      "source": ""
    },
    {
      "title": "'중동사태' 위기 극복…K패스 반값 할인·나프타 수급 안정 추경",
      "summary": "",
      "url": "https://finance.naver.com/news/news_read.naver?article_id=0000853827&office_id=422&mode=LSS2D&type=0&section_id=101&section_id2=261&section_id3=&date=20260411&page=1",
      "date": "",
      "source": ""
    },
    {
      "title": "GS 허태수 \"탑다운 방식은 한계...현장 실무자가 AI 주역 돼야\"",
      "summary": "",
      "url": "https://finance.naver.com/news/news_read.naver?article_id=0000104814&office_id=050&mode=LSS2D&type=0&section_id=101&section_id2=261&section_id3=&date=20260411&page=1",
      "date": "",
      "source": ""
    },
    {
      "title": "기후부, 추경 6162억 확정…재생E·취약계층 지원 확대",
      "summary": "",
      "url": "https://finance.naver.com/news/news_read.naver?article_id=0008883351&office_id=421&mode=LSS2D&type=0&section_id=101&section_id2=261&section_id3=&date=20260411&page=1",
      "date": "",
      "source": ""
    },
    {
      "title": "허태수 회장 \"AI를 '잘 쓰는' 나라로 도약할 때다\"",
      "summary": "",
      "url": "https://finance.naver.com/news/news_read.naver?article_id=0005505934&office_id=014&mode=LSS2D&type=0&section_id=101&section_id2=261&section_id3=&date=20260411&page=1",
      "date": "",
      "source": ""
    },
    {
      "title": "산업부, '공급망 안정화·피해 산업 지원' 추경 1조980억 확정",
      "summary": "",
      "url": "https://finance.naver.com/news/news_read.naver?article_id=0013881324&office_id=003&mode=LSS2D&type=0&section_id=101&section_id2=261&section_id3=&date=20260411&page=1",
      "date": "",
      "source": ""
    },
    {
      "title": "\"4대 분야 집중 지원\"…중기부, 추경 1조6903억원 확보",
      "summary": "",
      "url": "https://finance.naver.com/news/news_read.naver?article_id=0013881322&office_id=003&mode=LSS2D&type=0&section_id=101&section_id2=261&section_id3=&date=20260411&page=1",
      "date": "",
      "source": ""
    },
    {
      "title": "기후부, 추경 6162억 증액 확정…재생에너지 전환·취약계층 지원 확대",
      "summary": "",
      "url": "https://finance.naver.com/news/news_read.naver?article_id=0013881321&office_id=003&mode=LSS2D&type=0&section_id=101&section_id2=261&section_id3=&date=20260411&page=1",
      "date": "",
      "source": ""
    },
    {
      "title": "프랑스 프리미엄 조제식 노발락, 래퍼 트루디·전 야구선수 이대은 부부 육아 채널 '금똥이네..",
      "summary": "",
      "url": "https://finance.naver.com/news/news_read.naver?article_id=0000096148&office_id=243&mode=LSS2D&type=0&section_id=101&section_id2=261&section_id3=&date=20260411&page=1",
      "date": "",
      "source": ""
    },
    {
      "title": "중기부, 추경 1조 6903억 확정…수출 中企·소상공인·스타트업 집중 투입",
      "summary": "",
      "url": "https://finance.naver.com/news/news_read.naver?article_id=0008883330&office_id=421&mode=LSS2D&type=0&section_id=101&section_id2=261&section_id3=&date=20260411&page=1",
      "date": "",
      "source": ""
    },
    {
      "title": "농식품부, 추경 3천775억원 확정…유류·비료·사료 지원 확대",
      "summary": "",
      "url": "https://finance.naver.com/news/news_read.naver?article_id=0016015272&office_id=001&mode=LSS2D&type=0&section_id=101&section_id2=261&section_id3=&date=20260411&page=1",
      "date": "",
      "source": ""
    },
    {
      "title": "중기부, 추경 1조6천903억원 확정…수출中企·민생안정에 투입",
      "summary": "",
      "url": "https://finance.naver.com/news/news_read.naver?article_id=0016015271&office_id=001&mode=LSS2D&type=0&section_id=101&section_id2=261&section_id3=&date=20260411&page=1",
      "date": "",
      "source": ""
    },
    {
      "title": "어업·여객·중소선사 지원…해수부 추경 1448억 확정",
      "summary": "",
      "url": "https://finance.naver.com/news/news_read.naver?article_id=0013881303&office_id=003&mode=LSS2D&type=0&section_id=101&section_id2=261&section_id3=&date=20260411&page=1",
      "date": "",
      "source": ""
    },
    {
      "title": "HD현대중공업, 잠수함 화재 실종 직원 '사망자' 분류…구조는 아직",
      "summary": "",
      "url": "https://finance.naver.com/news/news_read.naver?article_id=0005342744&office_id=008&mode=LSS2D&type=0&section_id=101&section_id2=261&section_id3=&date=20260411&page=1",
      "date": "",
      "source": ""
    }
  ]
}